[{"date": "2024-09-14T08:30:17.403000+00:00", "session_key": 9593, "driver_number": 11, "meeting_key": 1245, "pit_duration": null, "lap_number": 1}, {"date": "2024-09-14T08:30:21.597000+00:00", "session_key": 9593, "driver_number": 24, "meeting_key": 1245, "pit_duration": null, "lap_number": 1}, {"date": "2024-09-14T08:30:29.779000+00:00", "session_key": 9593, "driver_number": 22, "meeting_key": 1245, "pit_duration": null, "lap_number": 1}, {"date": "2024-09-14T08:30:47.643000+00:00", "session_key": 9593, "driver_number": 77, "meeting_key": 1245, "pit_duration": null, "lap_number": 1}, {"date": "2024-09-14T08:30:50.114000+00:00", "session_key": 9593, "driver_number": 1, "meeting_key": 1245, "pit_duration": null, "lap_number": 1}, {"date": "2024-09-14T08:32:53.089000+00:00", "session_key": 9593, "driver_number": 18, "meeting_key": 1245, "pit_duration": null, "lap_number": 1}, {"date": "2024-09-14T08:33:01.423000+00:00", "session_key": 9593, "driver_number": 14, "meeting_key": 1245, "pit_duration": null, "lap_number": 1}, {"date": "2024-09-14T08:33:10.525000+00:00", "session_key": 9593, "meeting_key": 1245, "driver_number": 24, "pit_duration": 23.0, "lap_number": 2}, {"date": "2024-09-14T08:33:23.228000+00:00", "session_key": 9593, "meeting_key": 1245, "driver_number": 22, "pit_duration": 28.1, "lap_number": 2}, {"date": "2024-09-14T08:33:55.733000+00:00", "session_key": 9593, "meeting_key": 1245, "driver_number": 77, "pit_duration": 43.7, "lap_number": 2}, {"date": "2024-09-14T08:35:24.875000+00:00", "session_key": 9593, "meeting_key": 1245, "driver_number": 18, "pit_duration": 23.7, "lap_number": 2}, {"date": "2024-09-14T08:35:36.155000+00:00", "session_key": 9593, "meeting_key": 1245, "driver_number": 14, "pit_duration": 26.5, "lap_number": 2}, {"date": "2024-09-14T08:35:53.649000+00:00", "session_key": 9593, "meeting_key": 1245, "driver_number": 24, "pit_duration": 22.4, "lap_number": 3}, {"date": "2024-09-14T08:36:13.681000+00:00", "session_key": 9593, "meeting_key": 1245, "driver_number": 22, "pit_duration": 28.3, "lap_number": 3}, {"date": "2024-09-14T08:36:37.051000+00:00", "session_key": 9593, "meeting_key": 1245, "driver_number": 77, "pit_duration": 21.6, "lap_number": 3}, {"date": "2024-09-14T08:37:49.933000+00:00", "session_key": 9593, "meeting_key": 1245, "driver_number": 18, "pit_duration": 21.7, "lap_number": 3}, {"date": "2024-09-14T08:38:00.761000+00:00", "session_key": 9593, "meeting_key": 1245, "driver_number": 14, "pit_duration": 21.9, "lap_number": 3}, {"date": "2024-09-14T08:39:06.386000+00:00", "session_key": 9593, "meeting_key": 1245, "driver_number": 3, "pit_duration": null, "lap_number": 1}, {"date": "2024-09-14T08:41:41.184000+00:00", "session_key": 9593, "meeting_key": 1245, "driver_number": 3, "pit_duration": 24.5, "lap_number": 2}, {"date": "2024-09-14T08:42:07.237000+00:00", "session_key": 9593, "meeting_key": 1245, "driver_number": 24, "pit_duration": 232.4, "lap_number": 4}, {"date": "2024-09-14T08:42:09.673000+00:00", "session_key": 9593, "meeting_key": 1245, "driver_number": 77, "pit_duration": 205.6, "lap_number": 4}, {"date": "2024-09-14T08:42:17.775000+00:00", "session_key": 9593, "meeting_key": 1245, "driver_number": 4, "pit_duration": null, "lap_number": 1}, {"date": "2024-09-14T08:42:30.686000+00:00", "session_key": 9593, "meeting_key": 1245, "driver_number": 31, "pit_duration": null, "lap_number": 1}, {"date": "2024-09-14T08:42:37.510000+00:00", "session_key": 9593, "meeting_key": 1245, "driver_number": 55, "pit_duration": null, "lap_number": 1}, {"date": "2024-09-14T08:42:48.623000+00:00", "session_key": 9593, "meeting_key": 1245, "driver_number": 16, "pit_duration": null, "lap_number": 1}, {"date": "2024-09-14T08:43:12.029000+00:00", "session_key": 9593, "meeting_key": 1245, "driver_number": 10, "pit_duration": null, "lap_number": 1}, {"date": "2024-09-14T08:43:57.234000+00:00", "session_key": 9593, "meeting_key": 1245, "driver_number": 81, "pit_duration": null, "lap_number": 1}, {"date": "2024-09-14T08:44:13.507000+00:00", "session_key": 9593, "driver_number": 3, "meeting_key": 1245, "pit_duration": 25.8, "lap_number": 3}, {"date": "2024-09-14T08:54:03.606000+00:00", "session_key": 9593, "driver_number": 81, "meeting_key": 1245, "pit_duration": null, "lap_number": 2}, {"date": "2024-09-14T08:54:07.336000+00:00", "session_key": 9593, "driver_number": 63, "meeting_key": 1245, "pit_duration": null, "lap_number": 1}, {"date": "2024-09-14T08:54:11.562000+00:00", "session_key": 9593, "driver_number": 18, "meeting_key": 1245, "pit_duration": 856.8, "lap_number": 4}, {"date": "2024-09-14T08:54:19.534000+00:00", "session_key": 9593, "driver_number": 44, "meeting_key": 1245, "pit_duration": null, "lap_number": 1}, {"date": "2024-09-14T08:54:25.525000+00:00", "session_key": 9593, "driver_number": 4, "meeting_key": 1245, "pit_duration": null, "lap_number": 3}, {"date": "2024-09-14T08:54:29.337000+00:00", "session_key": 9593, "driver_number": 1, "meeting_key": 1245, "pit_duration": 1290.1, "lap_number": 2}, {"date": "2024-09-14T08:54:32.294000+00:00", "session_key": 9593, "driver_number": 55, "meeting_key": 1245, "pit_duration": null, "lap_number": 3}, {"date": "2024-09-14T08:54:40.124000+00:00", "session_key": 9593, "driver_number": 14, "meeting_key": 1245, "pit_duration": 873.6, "lap_number": 4}, {"date": "2024-09-14T08:54:48.623000+00:00", "session_key": 9593, "driver_number": 11, "meeting_key": 1245, "pit_duration": 1341.6, "lap_number": 2}, {"date": "2024-09-14T08:54:55.532000+00:00", "session_key": 9593, "driver_number": 16, "meeting_key": 1245, "pit_duration": null, "lap_number": 3}, {"date": "2024-09-14T08:54:58.014000+00:00", "session_key": 9593, "driver_number": 10, "meeting_key": 1245, "pit_duration": null, "lap_number": 2}, {"date": "2024-09-14T08:55:06.286000+00:00", "session_key": 9593, "driver_number": 3, "meeting_key": 1245, "pit_duration": 678.3, "lap_number": 4}, {"date": "2024-09-14T08:55:11.959000+00:00", "session_key": 9593, "driver_number": 24, "meeting_key": 1245, "pit_duration": 1016.9, "lap_number": 6}, {"date": "2024-09-14T08:55:14.583000+00:00", "session_key": 9593, "driver_number": 77, "meeting_key": 1245, "pit_duration": 990.3, "lap_number": 6}, {"date": "2024-09-14T08:55:27.489000+00:00", "session_key": 9593, "driver_number": 22, "meeting_key": 1245, "pit_duration": 1011.7, "lap_number": 4}, {"date": "2024-09-14T08:55:38.646000+00:00", "session_key": 9593, "meeting_key": 1245, "driver_number": 23, "pit_duration": null, "lap_number": 1}, {"date": "2024-09-14T08:55:45.163000+00:00", "session_key": 9593, "meeting_key": 1245, "driver_number": 43, "pit_duration": null, "lap_number": 1}, {"date": "2024-09-14T08:57:41.803000+00:00", "session_key": 9593, "meeting_key": 1245, "driver_number": 27, "pit_duration": null, "lap_number": 1}, {"date": "2024-09-14T09:00:00.446000+00:00", "session_key": 9593, "meeting_key": 1245, "driver_number": 50, "pit_duration": null, "lap_number": 1}, {"date": "2024-09-14T09:00:12.575000+00:00", "session_key": 9593, "meeting_key": 1245, "driver_number": 4, "pit_duration": 221.3, "lap_number": 4}, {"date": "2024-09-14T09:08:02.912000+00:00", "session_key": 9593, "meeting_key": 1245, "driver_number": 4, "pit_duration": 691.6, "lap_number": 6}, {"date": "2024-09-14T09:08:08.226000+00:00", "session_key": 9593, "meeting_key": 1245, "driver_number": 10, "pit_duration": null, "lap_number": 6}, {"date": "2024-09-14T09:08:14.948000+00:00", "session_key": 9593, "meeting_key": 1245, "driver_number": 27, "pit_duration": null, "lap_number": 4}, {"date": "2024-09-14T09:08:19.822000+00:00", "session_key": 9593, "meeting_key": 1245, "driver_number": 3, "pit_duration": 1472.1, "lap_number": 8}, {"date": "2024-09-14T09:08:21.643000+00:00", "session_key": 9593, "meeting_key": 1245, "driver_number": 77, "pit_duration": 1777.6, "lap_number": 10}, {"date": "2024-09-14T09:08:26.395000+00:00", "session_key": 9593, "meeting_key": 1245, "driver_number": 24, "pit_duration": 1811.6, "lap_number": 10}, {"date": "2024-09-14T09:08:33.591000+00:00", "session_key": 9593, "meeting_key": 1245, "driver_number": 43, "pit_duration": null, "lap_number": 5}, {"date": "2024-09-14T09:08:37.270000+00:00", "session_key": 9593, "meeting_key": 1245, "driver_number": 22, "pit_duration": 1801.5, "lap_number": 8}, {"date": "2024-09-14T09:08:51.715000+00:00", "session_key": 9593, "meeting_key": 1245, "driver_number": 44, "pit_duration": null, "lap_number": 5}, {"date": "2024-09-14T09:08:56.031000+00:00", "session_key": 9593, "meeting_key": 1245, "driver_number": 63, "pit_duration": null, "lap_number": 6}, {"date": "2024-09-14T09:08:59.651000+00:00", "session_key": 9593, "meeting_key": 1245, "driver_number": 18, "pit_duration": 1744.9, "lap_number": 9}, {"date": "2024-09-14T09:09:18.856000+00:00", "session_key": 9593, "meeting_key": 1245, "driver_number": 23, "pit_duration": null, "lap_number": 5}, {"date": "2024-09-14T09:09:31.273000+00:00", "session_key": 9593, "meeting_key": 1245, "driver_number": 16, "pit_duration": null, "lap_number": 7}, {"date": "2024-09-14T09:09:34.685000+00:00", "session_key": 9593, "meeting_key": 1245, "driver_number": 55, "pit_duration": null, "lap_number": 7}, {"date": "2024-09-14T09:11:22.827000+00:00", "session_key": 9593, "meeting_key": 1245, "driver_number": 1, "pit_duration": 2303.7, "lap_number": 6}, {"date": "2024-09-14T09:11:43.380000+00:00", "session_key": 9593, "meeting_key": 1245, "driver_number": 11, "pit_duration": 2356.7, "lap_number": 6}, {"date": "2024-09-14T09:12:37.413000+00:00", "session_key": 9593, "meeting_key": 1245, "driver_number": 81, "pit_duration": null, "lap_number": 7}, {"date": "2024-09-14T09:13:50.756000+00:00", "session_key": 9593, "meeting_key": 1245, "driver_number": 14, "pit_duration": 2024.6, "lap_number": 8}, {"date": "2024-09-14T09:17:13.723000+00:00", "session_key": 9593, "meeting_key": 1245, "driver_number": 63, "pit_duration": 20.6, "lap_number": 10}, {"date": "2024-09-14T09:17:20.856000+00:00", "session_key": 9593, "meeting_key": 1245, "driver_number": 43, "pit_duration": 173.0, "lap_number": 8}, {"date": "2024-09-14T09:17:52.595000+00:00", "session_key": 9593, "meeting_key": 1245, "driver_number": 44, "pit_duration": 22.6, "lap_number": 9}, {"date": "2024-09-14T09:18:16.608000+00:00", "session_key": 9593, "meeting_key": 1245, "driver_number": 18, "pit_duration": 208.5, "lap_number": 12}, {"date": "2024-09-14T09:18:20.248000+00:00", "session_key": 9593, "meeting_key": 1245, "driver_number": 3, "pit_duration": 251.1, "lap_number": 11}, {"date": "2024-09-14T09:18:29.681000+00:00", "session_key": 9593, "meeting_key": 1245, "driver_number": 16, "pit_duration": 180.3, "lap_number": 10}, {"date": "2024-09-14T09:18:36.218000+00:00", "session_key": 9593, "meeting_key": 1245, "driver_number": 55, "pit_duration": 184.7, "lap_number": 10}, {"date": "2024-09-14T09:18:52.050000+00:00", "session_key": 9593, "meeting_key": 1245, "driver_number": 1, "pit_duration": 116.3, "lap_number": 9}, {"date": "2024-09-14T09:19:32.093000+00:00", "session_key": 9593, "meeting_key": 1245, "driver_number": 22, "pit_duration": 276.6, "lap_number": 11}, {"date": "2024-09-14T09:19:48.939000+00:00", "session_key": 9593, "meeting_key": 1245, "driver_number": 23, "pit_duration": 270.3, "lap_number": 8}, {"date": "2024-09-14T09:20:25.043000+00:00", "session_key": 9593, "meeting_key": 1245, "driver_number": 10, "pit_duration": 389.9, "lap_number": 9}, {"date": "2024-09-14T09:20:53.913000+00:00", "session_key": 9593, "meeting_key": 1245, "driver_number": 81, "pit_duration": 22.4, "lap_number": 11}, {"date": "2024-09-14T09:21:46.318000+00:00", "session_key": 9593, "meeting_key": 1245, "driver_number": 24, "pit_duration": 185.6, "lap_number": 15}, {"date": "2024-09-14T09:21:49.028000+00:00", "session_key": 9593, "meeting_key": 1245, "driver_number": 77, "pit_duration": 453.2, "lap_number": 13}, {"date": "2024-09-14T09:21:56.830000+00:00", "session_key": 9593, "meeting_key": 1245, "driver_number": 27, "pit_duration": 365.9, "lap_number": 8}, {"date": "2024-09-14T09:22:19.285000+00:00", "session_key": 9593, "meeting_key": 1245, "driver_number": 4, "pit_duration": 401.2, "lap_number": 10}, {"date": "2024-09-14T09:22:24.942000+00:00", "session_key": 9593, "meeting_key": 1245, "driver_number": 14, "pit_duration": 153.5, "lap_number": 11}, {"date": "2024-09-14T09:24:58.586000+00:00", "session_key": 9593, "meeting_key": 1245, "driver_number": 16, "pit_duration": 16.7, "lap_number": 13}, {"date": "2024-09-14T09:28:43.039000+00:00", "session_key": 9593, "meeting_key": 1245, "driver_number": 81, "pit_duration": 336.8, "lap_number": 12}, {"date": "2024-09-14T09:29:08.758000+00:00", "session_key": 9593, "meeting_key": 1245, "driver_number": 43, "pit_duration": 130.5, "lap_number": 13}, {"date": "2024-09-14T09:29:11.469000+00:00", "session_key": 9593, "meeting_key": 1245, "driver_number": 23, "pit_duration": 78.7, "lap_number": 12}]